aniposelib/__init__.py
aniposelib/boards.py
aniposelib/cameras.py
aniposelib/utils.py
aniposelib-0.7.2.dist-info/licenses/LICENSE
aniposelib-0.7.2.dist-info/METADATA
aniposelib-0.7.2.dist-info/WHEEL
aniposelib-0.7.2.dist-info/top_level.txt
aniposelib-0.7.2.dist-info/RECORD
