Metadata-Version: 2.4
Name: aniposelib
Version: 0.7.2
Summary: An easy-to-use library for calibrating cameras in python, made for Anipose
Home-page: https://github.com/lambdaloop/aniposelib
Author: Lili Karashchuk
Author-email: lili.karashchuk@gmail.com
Classifier: Programming Language :: Python :: 3
Classifier: License :: OSI Approved :: BSD License
Classifier: Intended Audience :: Science/Research
Classifier: Topic :: Scientific/Engineering
Classifier: Topic :: Scientific/Engineering :: Image Recognition
License-File: LICENSE
Requires-Dist: opencv-contrib-python>=4.7.0.68
Requires-Dist: numba
Requires-Dist: pandas
Requires-Dist: numpy
Requires-Dist: scipy
Requires-Dist: toml
Requires-Dist: tqdm
Dynamic: author
Dynamic: author-email
Dynamic: classifier
Dynamic: description
Dynamic: description-content-type
Dynamic: home-page
Dynamic: license-file
Dynamic: requires-dist
Dynamic: summary
